100_days_grind/3_bit_majority/majority_3bit_tb.sv
module majority3_tb ();
   reg [2:0]i;
   wire out;

   initial begin
    i = 3'b000; #4
    i = 3'b001; #4
    i = 3'b010; #4
    i = 3'b011; #4
    i = 3'b100; #4
    i = 3'b101; #4
    i = 3'b110; #4
    i = 3'b111; #4
    i = 3'b000; #4
    $finish;
    end 

    initial begin
        $dumpfile("majority3.vcd");
        $dumpvars;
    end
endmodule

100_days_grind/3_bit_majority/majority_3bit.sv
module majority3 (i,out);
input [2:0]i;
output out;

assign out = (i[1] & i[2]) or (i[0] & (i[1] or i[2]));

endmodule

100_days_grind/3_bit_majority/majority3.vcd
$date
	Thu Sep 14 23:05:26 2023
$end
$version
	Icarus Verilog
$end
$timescale
	1s
$end
$scope module majority3 $end
$var wire 3 ! i [2:0] $end
$var wire 1 " out $end
$upscope $end
$scope module majority3_tb $end
$var reg 3 # i [2:0] $end
$upscope $end
$enddefinitions $end
#0
$dumpvars
b0 #
x"
bz !
$end
#4
b1 #
#8
b10 #
#12
b11 #
#16
b100 #
#20
b101 #
#24
b110 #
#28
b111 #
#32
b0 #
