100_days_grind/3_bit_majority/majority_3bit.sv
module majority3 (i,out);
input [2:0]i;
output out;
wire w1,w2,w3,w4;
and (w1,i[1],i[2]);
or (w2,i[1],i[2]);
and(w3,i[0],w2);
or(out,w1,w3);

endmodule

100_days_grind/3_bit_majority/majority_3bit_tb.sv
module majority3_tb ();
   reg [2:0]i;
   wire out;

   majority3 yu (.i(i),.out(out));

   initial begin
    i = 3'b000; #4
    i = 3'b001; #4
    i = 3'b010; #4
    i = 3'b011; #4
    i = 3'b100; #4
    i = 3'b101; #4
    i = 3'b110; #4
    i = 3'b111; #4
    i = 3'b000; #4
    $finish;
    end 

    initial begin
        $dumpfile("majority3.vcd");
        $dumpvars;
    end
endmodule

100_days_grind/3_bit_majority/majority3.vcd
$date
	Sat Sep 16 19:50:55 2023
$end
$version
	Icarus Verilog
$end
$timescale
	1s
$end
$scope module majority3_tb $end
$var wire 1 ! out $end
$var reg 3 " i [2:0] $end
$scope module yu $end
$var wire 3 # i [2:0] $end
$var wire 1 ! out $end
$var wire 1 $ w1 $end
$var wire 1 % w2 $end
$var wire 1 & w3 $end
$upscope $end
$upscope $end
$enddefinitions $end
#0
$dumpvars
0&
0%
0$
b0 #
b0 "
0!
$end
#4
b1 "
b1 #
#8
1%
b10 "
b10 #
#12
1!
1&
b11 "
b11 #
#16
0!
0&
b100 "
b100 #
#20
1!
1&
b101 "
b101 #
#24
1$
0&
b110 "
b110 #
#28
1&
b111 "
b111 #
#32
0!
0$
0%
0&
b0 "
b0 #
