Practice_beginning/count_specific_value/pre_clr.sv
module pre_clr (q,qbar,clk,pre,clr,j,k);
input clk,pre,clr,j,k;
output reg q = 0, qbar = 1;

    always @( posedge clk) begin
        case ({j,k})
        2'b00 : q = q;
        2'b01 : q = 0;
        2'b10 : q = 1;
        2'b11 : q = ~q;
        endcase
        qbar = ~q;
    end
 
    always @ (*) begin 
        if (pre == 0 && clr == 1)
        q = 1;
        else if (pre == 1 && clr == 0)
        q = 0;
        else
        q = q;

        qbar = ~q;
    end
endmodule

Practice_beginning/count_specific_value/pre_clr_tb.sv
module pre_clr_tb();
reg clk,pre,clr,j,k;
wire q,qbar;

pre_clr gh (.q(q),.qbar(qbar),.clk(clk),.clr(clr),.j(j),.k(k),.pre(pre));

initial begin
    clk = 0; pre = 1; clr = 1;
    j = 0; k = 0; #10
    j = 1; k = 0; #10
    clr = 0; #2
    clr = 1; #2
    j = 1; k = 0; #10
    j = 1; k = 1; #10
    j = 0; k = 1; #10
    j = 1; k = 1; #10
    $finish;
end

always #5 clk = ~clk;

initial begin
    $dumpfile("pre_clr_test.vcd");
    $dumpvars;
end
endmodule

Practice_beginning/count_specific_value/pre_clr_test.vcd
$date
	Tue Sep 12 23:02:48 2023
$end
$version
	Icarus Verilog
$end
$timescale
	1s
$end
$scope module pre_clr_tb $end
$var wire 1 ! qbar $end
$var wire 1 " q $end
$var reg 1 # clk $end
$var reg 1 $ clr $end
$var reg 1 % j $end
$var reg 1 & k $end
$var reg 1 ' pre $end
$scope module gh $end
$var wire 1 # clk $end
$var wire 1 $ clr $end
$var wire 1 % j $end
$var wire 1 & k $end
$var wire 1 ' pre $end
$var reg 1 " q $end
$var reg 1 ! qbar $end
$upscope $end
$upscope $end
$enddefinitions $end
#0
$dumpvars
1'
0&
0%
1$
0#
0"
1!
$end
#5
1#
#10
0#
1%
#15
0!
1"
1#
#20
1!
0"
0#
0$
#22
1$
#25
0!
1"
1#
#30
0#
#34
1&
#35
1!
0"
1#
#40
0#
#44
0%
#45
1#
#50
0#
#54
1%
#55
0!
1"
1#
