100_days_grind/parity_generator/parity_even_odd.sv
module p_e_o (i,oe,od);
input [3:0]i;
output oe,od;
wire w1,w2,w3,w4;

xor(w1,i[0],i[1]);
xor(w2,i[2],i[3]);
xor(oe,w1,w2);
xnor(w3,i[0],i[1]);
xnor(w4,i[2],i[3]);
xnor(od,w3,w4);

endmodule

100_days_grind/parity_generator/parity_even_odd_tb.sv
module p_e_o_tb();
reg [3:0]i;
wire oe,od;

p_e_o yu (i,oe,od);

initial begin
    i=4'b0000; #10
    i=4'b0001; #10
    i=4'b0010; #10
    i=4'b0011; #10
    i=4'b0100; #10
    i=4'b0101; #10
    i=4'b0110; #10
    i=4'b0111; #10
    i=4'b1000; #10
    i=4'b1001; #10
    i=4'b1010; #10
    i=4'b1011; #10
    i=4'b1100; #10
    i=4'b1101; #10
    $finish;
end

initial begin
    $dumpfile("p_e_o_test.vcd");
    $dumpvars;
end

endmodule

100_days_grind/parity_generator/p_e_o_test.vcd
$date
	Sun Sep 17 10:50:12 2023
$end
$version
	Icarus Verilog
$end
$timescale
	1s
$end
$scope module p_e_o_tb $end
$var wire 1 ! oe $end
$var wire 1 " od $end
$var reg 4 # i [3:0] $end
$scope module yu $end
$var wire 4 $ i [3:0] $end
$var wire 1 " od $end
$var wire 1 ! oe $end
$var wire 1 % w1 $end
$var wire 1 & w2 $end
$var wire 1 ' w3 $end
$var wire 1 ( w4 $end
$upscope $end
$upscope $end
$enddefinitions $end
#0
$dumpvars
1(
1'
0&
0%
b0 $
b0 #
1"
0!
$end
#10
1!
0"
1%
0'
b1 #
b1 $
#20
b10 #
b10 $
#30
0!
1"
0%
1'
b11 #
b11 $
#40
1!
0"
1&
0(
b100 #
b100 $
#50
0!
1"
1%
0'
b101 #
b101 $
#60
b110 #
b110 $
#70
1!
0"
0%
1'
b111 #
b111 $
#80
b1000 #
b1000 $
#90
0!
1"
1%
0'
b1001 #
b1001 $
#100
b1010 #
b1010 $
#110
1!
0"
0%
1'
b1011 #
b1011 $
#120
0!
1"
0&
1(
b1100 #
b1100 $
#130
1!
0"
1%
0'
b1101 #
b1101 $
