Practice_beginning/my_counter/my_counter.v
module my_counter (clk,rst,out);
input  clk,rst;
output [3:0]out;
reg [3:0]out;

always @ (posedge clk)
begin
    if (rst == 1)
    out <= 4'b0000;
    else
        out <= out +1;
end
endmodule

Practice_beginning/my_counter/my_counter_tb.v
module my_counter_tb();
reg clk,rst;
wire [3:0]count;

my_counter ha (.clk(clk),.rst(rst),.out(count));

initial begin
    clk = 1'b0; rst = 1'b1;
    #100 rst = 1'b0;
    #2000 $finish;
end
always #50 clk = ~clk;
initial begin
    $dumpfile("count.vcd");
    $dumpvars;
    $monitor("%d,%b,%b,%d",$time,clk,rst,count);
end
endmodule

Practice_beginning/my_counter/count.vcd
$date
	Sun Aug 20 19:20:19 2023
$end
$version
	Icarus Verilog
$end
$timescale
	1s
$end
$scope module my_counter_tb $end
$var wire 4 ! count [3:0] $end
$var reg 1 " clk $end
$var reg 1 # rst $end
$scope module ha $end
$var wire 1 " clk $end
$var wire 1 # rst $end
$var reg 4 $ out [3:0] $end
$upscope $end
$upscope $end
$enddefinitions $end
#0
$dumpvars
bx $
1#
0"
bx !
$end
#50
b0 !
b0 $
1"
#100
0"
0#
#150
b1 !
b1 $
1"
#200
0"
#250
b10 !
b10 $
1"
#300
0"
#350
b11 !
b11 $
1"
#400
0"
#450
b100 !
b100 $
1"
#500
0"
#550
b101 !
b101 $
1"
#600
0"
#650
b110 !
b110 $
1"
#700
0"
#750
b111 !
b111 $
1"
#800
0"
#850
b1000 !
b1000 $
1"
#900
0"
#950
b1001 !
b1001 $
1"
#1000
0"
#1050
b1010 !
b1010 $
1"
#1100
0"
#1150
b1011 !
b1011 $
1"
#1200
0"
#1250
b1100 !
b1100 $
1"
#1300
0"
#1350
b1101 !
b1101 $
1"
#1400
0"
#1450
b1110 !
b1110 $
1"
#1500
0"
#1550
b1111 !
b1111 $
1"
#1600
0"
#1650
b0 !
b0 $
1"
#1700
0"
#1750
b1 !
b1 $
1"
#1800
0"
#1850
b10 !
b10 $
1"
#1900
0"
#1950
b11 !
b11 $
1"
#2000
0"
#2050
b100 !
b100 $
1"
