100_days_grind/up_down_counter/jk_ff.sv
module jk (j,k,clk,q,qbar);
input j,k,clk;
output reg q = 0,qbar = 1;
always @(posedge clk) begin
    case({j,k}) 
    2'b00 : begin
        q = q;
    end
    2'b01 : begin
        q = 0;
    end
    2'b10 : begin
        q = 1;
    end
    2'b11 : begin
        q = ~q;
    end
    endcase
    qbar = ~q;
end
endmodule

Practice_beginning/jk_flipflop/jk_tb.sv
module jk_tb ();
  reg j,k,clk;
  wire q,qbar;

  jk haha (.j(j),.k(k),.clk(clk),.q(q),.qbar(qbar));

  initial begin
    clk = 0;
    j = 0; k= 0; #10
    j = 0; k= 1; #10
    j = 1; k= 0; #10
    j = 1; k= 1; #30
  $finish;
  end  

  always #5 clk = ~clk;

  initial begin
    $dumpfile("jk_test.vcd");
    $dumpvars;
  end
endmodule

Practice_beginning/jk_flipflop/jk_test.vcd
$date
	Fri Sep  8 18:08:02 2023
$end
$version
	Icarus Verilog
$end
$timescale
	1s
$end
$scope module jk_tb $end
$var wire 1 ! qbar $end
$var wire 1 " q $end
$var reg 1 # clk $end
$var reg 1 $ j $end
$var reg 1 % k $end
$scope module haha $end
$var wire 1 # clk $end
$var wire 1 $ j $end
$var wire 1 % k $end
$var reg 1 " q $end
$var reg 1 ! qbar $end
$upscope $end
$upscope $end
$enddefinitions $end
#0
$dumpvars
0%
0$
0#
0"
1!
$end
#5
1#
#10
0#
1%
#15
1#
#20
0#
0%
1$
#25
0!
1"
1#
#30
0#
1%
#35
1!
0"
1#
#40
0#
#45
0!
1"
1#
#50
0#
#55
1!
0"
1#
