100_days_grind/freq_div_4/dff_task.v
module dff_ta();
  task dff_y;
  input reg d;
  output reg q;
  output reg qbar;
    begin
        if (d == 0)begin
            q = 0;
            qbar = ~q;
        end
          
        else begin
            q = 1;
            qbar = ~q;
        end
    end
  endtask 
endmodule

100_days_grind/freq_div_4/dff.v
module dff_gh(d,clk,q,qbar);

dff_ta gh();

input d,clk;
output reg q = 0; 
output reg qbar = 1;

always @(posedge clk) begin
    gh.dff_y(d,q,qbar);
end

endmodule

100_days_grind/freq_div_4/freq_2.v
module freq_2 (clk,out);
input clk;
output out;
wire w1;
dff_gh yu(w1,clk,out,w1);
assign d = w1;
assign qbar = w1;

endmodule

100_days_grind/freq_div_4/freq_2_tb.v
module freq_2_tb();

freq_2 ty (.clk(clk),.out(out));

reg clk;
wire out;

initial begin
    clk = 0; #160
    $finish;
end

always #2 clk = ~clk;

initial begin
    $dumpfile("freq_test.vcd");
    $dumpvars;
end

endmodule

100_days_grind/freq_div_4/freq_test.vcd
$date
	Thu Oct 12 23:34:43 2023
$end
$version
	Icarus Verilog
$end
$timescale
	1s
$end
$scope module freq_2_tb $end
$var wire 1 ! out $end
$var reg 1 " clk $end
$scope module ty $end
$var wire 1 " clk $end
$var wire 1 # d $end
$var wire 1 $ qbar $end
$var wire 1 % w1 $end
$var wire 1 ! out $end
$scope module yu $end
$var wire 1 " clk $end
$var wire 1 % d $end
$var reg 1 ! q $end
$var reg 1 % qbar $end
$scope module gh $end
$scope task dff_y $end
$var reg 1 & d $end
$var reg 1 ' q $end
$var reg 1 ( qbar $end
$upscope $end
$upscope $end
$upscope $end
$upscope $end
$upscope $end
$enddefinitions $end
#0
$dumpvars
x(
x'
x&
1%
1$
1#
0"
0!
$end
#2
0$
0#
0%
1!
0(
1'
1&
1"
#4
0"
#6
1$
1#
1%
0!
1(
0'
0&
1"
#8
0"
#10
0$
0#
0%
1!
0(
1'
1&
1"
#12
0"
#14
1$
1#
1%
0!
1(
0'
0&
1"
#16
0"
#18
0$
0#
0%
1!
0(
1'
1&
1"
#20
0"
#22
1$
1#
1%
0!
1(
0'
0&
1"
#24
0"
#26
0$
0#
0%
1!
0(
1'
1&
1"
#28
0"
#30
1$
1#
1%
0!
1(
0'
0&
1"
#32
0"
#34
0$
0#
0%
1!
0(
1'
1&
1"
#36
0"
#38
1$
1#
1%
0!
1(
0'
0&
1"
#40
0"
#42
0$
0#
0%
1!
0(
1'
1&
1"
#44
0"
#46
1$
1#
1%
0!
1(
0'
0&
1"
#48
0"
#50
0$
0#
0%
1!
0(
1'
1&
1"
#52
0"
#54
1$
1#
1%
0!
1(
0'
0&
1"
#56
0"
#58
0$
0#
0%
1!
0(
1'
1&
1"
#60
0"
#62
1$
1#
1%
0!
1(
0'
0&
1"
#64
0"
#66
0$
0#
0%
1!
0(
1'
1&
1"
#68
0"
#70
1$
1#
1%
0!
1(
0'
0&
1"
#72
0"
#74
0$
0#
0%
1!
0(
1'
1&
1"
#76
0"
#78
1$
1#
1%
0!
1(
0'
0&
1"
#80
0"
#82
0$
0#
0%
1!
0(
1'
1&
1"
#84
0"
#86
1$
1#
1%
0!
1(
0'
0&
1"
#88
0"
#90
0$
0#
0%
1!
0(
1'
1&
1"
#92
0"
#94
1$
1#
1%
0!
1(
0'
0&
1"
#96
0"
#98
0$
0#
0%
1!
0(
1'
1&
1"
#100
0"
#102
1$
1#
1%
0!
1(
0'
0&
1"
#104
0"
#106
0$
0#
0%
1!
0(
1'
1&
1"
#108
0"
#110
1$
1#
1%
0!
1(
0'
0&
1"
#112
0"
#114
0$
0#
0%
1!
0(
1'
1&
1"
#116
0"
#118
1$
1#
1%
0!
1(
0'
0&
1"
#120
0"
#122
0$
0#
0%
1!
0(
1'
1&
1"
#124
0"
#126
1$
1#
1%
0!
1(
0'
0&
1"
#128
0"
#130
0$
0#
0%
1!
0(
1'
1&
1"
#132
0"
#134
1$
1#
1%
0!
1(
0'
0&
1"
#136
0"
#138
0$
0#
0%
1!
0(
1'
1&
1"
#140
0"
#142
1$
1#
1%
0!
1(
0'
0&
1"
#144
0"
#146
0$
0#
0%
1!
0(
1'
1&
1"
#148
0"
#150
1$
1#
1%
0!
1(
0'
0&
1"
#152
0"
#154
0$
0#
0%
1!
0(
1'
1&
1"
#156
0"
#158
1$
1#
1%
0!
1(
0'
0&
1"
