100_days_grind/up_down_counter/jk_ff.sv
module jk (j,k,clk,q,qbar);
input j,k,clk;
output reg q = 0,qbar = 1;
always @(posedge clk) begin
    case({j,k}) 
    2'b00 : begin
        q = q;
    end
    2'b01 : begin
        q = 0;
    end
    2'b10 : begin
        q = 1;
    end
    2'b11 : begin
        q = ~q;
    end
    endcase
    qbar = ~q;
end
endmodule

100_days_grind/up_down_counter/mux21.sv
module mux21 (i,s,out);
input [1:0]i;
input s;
output out;

assign out = s ? i[1]:i[0];

endmodule

100_days_grind/up_down_counter/four_up_down.sv
module four_up_down_counter(clk,m,out);
input clk,m;
output [3:0]out;
wire w1,w2,w3,w4,w5,w6,w7,w8,w9;

jk gh (.j(1'b1),.k(1'b1),.clk(clk),.q(w1),.qbar(w2));
mux21 jk (.i({w1,w2}),.s(m),.out(w3));
jk hj (.j(1'b1),.k(1'b1),.clk(w3),.q(w4),.qbar(w5));
mux21 kl (.i({w4,w5}),.s(m),.out(w6));
jk yu (.j(1'b1),.k(1'b1),.clk(w6),.q(w7),.qbar(w8));
mux21 lp (.i({w7,w8}),.s(m),.out(w9));
jk po (.j(1'b1),.k(1'b1),.clk(w9),.q(out[3]));

assign out[0] = w1;
assign out[1] = w4;
assign out[2] = w7;

endmodule

100_days_grind/up_down_counter/four_up_down_tb.sv
module four_up_down_counter_tb();
reg clk,m;
wire [3:0]out;

four_up_down_counter yu (clk,m,out);

initial begin
    clk = 0;
    m = 0; #60
    m = 1; #60
    $finish;
end

always #2 clk = ~clk;

initial begin
    $dumpfile("four_up_down_counter.vcd");
    $dumpvars;
end

endmodule

100_days_grind/up_down_counter/four_up_down_counter.vcd
$date
	Mon Sep 11 22:58:38 2023
$end
$version
	Icarus Verilog
$end
$timescale
	1s
$end
$scope module four_up_down_counter_tb $end
$var wire 4 ! out [3:0] $end
$var reg 1 " clk $end
$var reg 1 # m $end
$scope module yu $end
$var wire 1 " clk $end
$var wire 1 # m $end
$var wire 1 $ w9 $end
$var wire 1 % w8 $end
$var wire 1 & w7 $end
$var wire 1 ' w6 $end
$var wire 1 ( w5 $end
$var wire 1 ) w4 $end
$var wire 1 * w3 $end
$var wire 1 + w2 $end
$var wire 1 , w1 $end
$var wire 4 - out [3:0] $end
$scope module gh $end
$var wire 1 " clk $end
$var wire 1 . j $end
$var wire 1 / k $end
$var reg 1 , q $end
$var reg 1 + qbar $end
$upscope $end
$scope module hj $end
$var wire 1 0 j $end
$var wire 1 1 k $end
$var wire 1 * clk $end
$var reg 1 ) q $end
$var reg 1 ( qbar $end
$upscope $end
$scope module jk $end
$var wire 2 2 i [1:0] $end
$var wire 1 # s $end
$var wire 1 * out $end
$upscope $end
$scope module kl $end
$var wire 2 3 i [1:0] $end
$var wire 1 # s $end
$var wire 1 ' out $end
$upscope $end
$scope module lp $end
$var wire 2 4 i [1:0] $end
$var wire 1 # s $end
$var wire 1 $ out $end
$upscope $end
$scope module po $end
$var wire 1 $ clk $end
$var wire 1 5 j $end
$var wire 1 6 k $end
$var reg 1 7 q $end
$var reg 1 8 qbar $end
$upscope $end
$scope module yu $end
$var wire 1 ' clk $end
$var wire 1 9 j $end
$var wire 1 : k $end
$var reg 1 & q $end
$var reg 1 % qbar $end
$upscope $end
$upscope $end
$upscope $end
$enddefinitions $end
#0
$dumpvars
1:
19
08
17
16
15
b10 4
b10 3
b1 2
11
10
1/
1.
b1110 -
0,
1+
1*
1)
0(
0'
1&
0%
0$
0#
0"
b1110 !
$end
#2
0*
0+
b10 2
b1111 !
b1111 -
1,
1"
#4
0"
#6
18
07
1$
1%
b1 4
0&
1'
1(
b1 3
0)
1*
1+
b1 2
b0 !
b0 -
0,
1"
#8
0"
#10
0*
0+
b10 2
b1 !
b1 -
1,
1"
#12
0"
#14
0'
0(
b10 3
1)
1*
1+
b1 2
b10 !
b10 -
0,
1"
#16
0"
#18
0*
0+
b10 2
b11 !
b11 -
1,
1"
#20
0"
#22
0$
0%
b10 4
1&
1'
1(
b1 3
0)
1*
1+
b1 2
b100 !
b100 -
0,
1"
#24
0"
#26
0*
0+
b10 2
b101 !
b101 -
1,
1"
#28
0"
#30
0'
0(
b10 3
1)
1*
1+
b1 2
b110 !
b110 -
0,
1"
#32
0"
#34
0*
0+
b10 2
b111 !
b111 -
1,
1"
#36
0"
#38
08
17
1$
1%
b1 4
0&
1'
1(
b1 3
0)
1*
1+
b1 2
b1000 !
b1000 -
0,
1"
#40
0"
#42
0*
0+
b10 2
b1001 !
b1001 -
1,
1"
#44
0"
#46
0'
0(
b10 3
1)
1*
1+
b1 2
b1010 !
b1010 -
0,
1"
#48
0"
#50
0*
0+
b10 2
b1011 !
b1011 -
1,
1"
#52
0"
#54
0$
0%
b10 4
1&
1'
1(
b1 3
0)
1*
1+
b1 2
b1100 !
b1100 -
0,
1"
#56
0"
#58
0*
0+
b10 2
b1101 !
b1101 -
1,
1"
#60
1%
b1 4
0&
0(
b10 3
1)
18
b11 !
b11 -
07
1*
1'
0$
0"
1#
#62
0*
1+
b1 2
b10 !
b10 -
0,
1"
#64
0"
#66
0'
1(
b1 3
0)
1*
0+
b10 2
b1 !
b1 -
1,
1"
#68
0"
#70
0*
1+
b1 2
b0 !
b0 -
0,
1"
#72
0"
#74
08
17
1$
0%
b10 4
1&
1'
0(
b10 3
1)
1*
0+
b10 2
b1111 !
b1111 -
1,
1"
#76
0"
#78
0*
1+
b1 2
b1110 !
b1110 -
0,
1"
#80
0"
#82
0'
1(
b1 3
0)
1*
0+
b10 2
b1101 !
b1101 -
1,
1"
#84
0"
#86
0*
1+
b1 2
b1100 !
b1100 -
0,
1"
#88
0"
#90
0$
1%
b1 4
0&
1'
0(
b10 3
1)
1*
0+
b10 2
b1011 !
b1011 -
1,
1"
#92
0"
#94
0*
1+
b1 2
b1010 !
b1010 -
0,
1"
#96
0"
#98
0'
1(
b1 3
0)
1*
0+
b10 2
b1001 !
b1001 -
1,
1"
#100
0"
#102
0*
1+
b1 2
b1000 !
b1000 -
0,
1"
#104
0"
#106
18
07
1$
0%
b10 4
1&
1'
0(
b10 3
1)
1*
0+
b10 2
b111 !
b111 -
1,
1"
#108
0"
#110
0*
1+
b1 2
b110 !
b110 -
0,
1"
#112
0"
#114
0'
1(
b1 3
0)
1*
0+
b10 2
b101 !
b101 -
1,
1"
#116
0"
#118
0*
1+
b1 2
b100 !
b100 -
0,
1"
