100_days_grind/sipo_shift_register/dff_task.sv
module dff_task(d,clk,q);

input d,clk;
output reg q = 0;

always @(posedge clk) begin
   q <= d;
end

endmodule

100_days_grind/sipo_shift_register/sipo.sv
module sipo(d,clk,o);

input d,clk;
output [3:0]o;
wire w1,w2,w3;

dff_task ty (.d(d),.clk(clk),.q(w1));
dff_task yu (.d(w1),.clk(clk),.q(w2));
dff_task ui (.d(w2),.clk(clk),.q(w3));
dff_task tj (.d(w3),.clk(clk),.q(o[3]));

assign o[0] = w1;
assign o[1] = w2;
assign o[2] = w3;

endmodule

100_days_grind/sipo_shift_register/sipo_tb.sv
module sipo_tb();

reg d,clk;
wire [3:0]o;

sipo io (.d(d),.clk(clk),.o(o));

initial begin
    clk = 0; 
    d = 0; #2
    d = 1; #2
    d = 0; #2
    d = 1; #2
    d = 1; #2
    d = 0; #2
    d = 0; #2
    d = 1; #2
    d = 0; #2
    d = 1; #2
    d = 1; #2
    d = 0; #2
    d = 1; #2
    d = 0; #2
    d = 0; #2
    d = 1; #2
    d = 0; #2
    d = 1; #2
    d = 0; #2
    d = 1; #2
    $finish;
end

initial begin
    $dumpfile("siop_test.vcd");
    $dumpvars;
end

always #2 clk = ~clk;

endmodule

100_days_grind/sipo_shift_register/siop_test.vcd
$date
	Sun Oct 15 11:55:26 2023
$end
$version
	Icarus Verilog
$end
$timescale
	1s
$end
$scope module sipo_tb $end
$var wire 4 ! o [3:0] $end
$var reg 1 " clk $end
$var reg 1 # d $end
$scope module io $end
$var wire 1 " clk $end
$var wire 1 # d $end
$var wire 1 $ w3 $end
$var wire 1 % w2 $end
$var wire 1 & w1 $end
$var wire 4 ' o [3:0] $end
$scope module tj $end
$var wire 1 " clk $end
$var wire 1 $ d $end
$var reg 1 ( q $end
$upscope $end
$scope module ty $end
$var wire 1 " clk $end
$var wire 1 # d $end
$var reg 1 & q $end
$upscope $end
$scope module ui $end
$var wire 1 " clk $end
$var wire 1 % d $end
$var reg 1 $ q $end
$upscope $end
$scope module yu $end
$var wire 1 " clk $end
$var wire 1 & d $end
$var reg 1 % q $end
$upscope $end
$upscope $end
$upscope $end
$enddefinitions $end
#0
$dumpvars
0(
b0 '
0&
0%
0$
0#
0"
b0 !
$end
#2
b1 !
b1 '
1&
1"
1#
#4
0"
0#
#6
1(
1$
b1111 !
b1111 '
1%
1"
1#
#8
0"
#10
b1110 !
b1110 '
0&
1"
0#
#12
0"
#14
b1111 !
b1111 '
1&
1"
1#
#16
0"
0#
#18
1"
1#
#20
0"
#22
0(
0$
0%
b0 !
b0 '
0&
1"
0#
#24
0"
1#
#26
1"
0#
#28
0"
#30
1(
1$
1%
b1111 !
b1111 '
1&
1"
1#
#32
0"
0#
#34
1"
1#
#36
0"
0#
#38
1"
1#
