100_days_grind/modn_counter/pre_clr_jk.sv
module pre_clr (q,qbar,clk,pre,clr,j,k);
input clk,pre,clr,j,k;
output reg q = 0, qbar = 1;

    always @( posedge clk) begin
        case ({j,k})
        2'b00 : q = q;
        2'b01 : q = 0;
        2'b10 : q = 1;
        2'b11 : q = ~q;
        endcase
        qbar = ~q;
    end
 
    always @ (*) begin 
        if (pre == 0)
        q = 1;
        else if (clr == 0)
        q = 0;
        else
        q = q;

        qbar = ~q;
    end
endmodule

100_days_grind/modn_counter/modn_count.sv
// THis is a mod n counter or to be specific it counts to a perticular value.
// In this example the counter counts till 5 and then resets back;

module modn_counter (clk,out);

input clk;
output [2:0]out;
wire w1,w2,w3,w4,wz;

assign wz = w1 & w2 & ~w3;
pre_clr gh (.j(1'b1),.k(1'b1),.pre(wz),.clr(1'b1),.clk(clk),.q(w1));
pre_clr hj (.j(1'b1),.k(1'b1),.pre(wz),.clr(1'b1),.clk(w1),.q(w2));
pre_clr op (.j(1'b1),.k(1'b1),.pre(wz),.clr(1'b1),.clk(w2),.q(w3));
assign out[0] = w1;
assign out[1] = w2;
assign out[2] = w3;
endmodule

100_days_grind/modn_counter/modn_count_tb.sv
module modn_coun_tb();
reg clk;
wire [2:0]out;

modn_counter yu(.clk(clk),.out(out));

initial begin
    clk = 0; #250
    $finish;
end

always #5 clk = ~clk;

initial begin
    $dumpfile("modn_count.vcd");
    $dumpvars;
end

endmodule

100_days_grind/modn_counter/modn_count.vcd
$date
	Wed Sep 13 20:20:08 2023
$end
$version
	Icarus Verilog
$end
$timescale
	1s
$end
$scope module modn_coun_tb $end
$var wire 3 ! out [2:0] $end
$var reg 1 " clk $end
$scope module yu $end
$var wire 1 " clk $end
$var wire 1 # wz $end
$var wire 1 $ w3 $end
$var wire 1 % w2 $end
$var wire 1 & w1 $end
$var wire 3 ' out [2:0] $end
$scope module gh $end
$var wire 1 " clk $end
$var wire 1 ( clr $end
$var wire 1 ) j $end
$var wire 1 * k $end
$var wire 1 # pre $end
$var reg 1 & q $end
$var reg 1 + qbar $end
$upscope $end
$scope module hj $end
$var wire 1 & clk $end
$var wire 1 , clr $end
$var wire 1 - j $end
$var wire 1 . k $end
$var wire 1 # pre $end
$var reg 1 % q $end
$var reg 1 / qbar $end
$upscope $end
$scope module op $end
$var wire 1 " clk $end
$var wire 1 0 clr $end
$var wire 1 1 j $end
$var wire 1 2 k $end
$var wire 1 # pre $end
$var reg 1 $ q $end
$var reg 1 3 qbar $end
$upscope $end
$upscope $end
$upscope $end
$enddefinitions $end
#0
$dumpvars
03
12
11
10
0/
1.
1-
1,
0+
1*
1)
1(
b111 '
1&
1%
1$
0#
0"
b111 !
$end
#5
0/
1%
0+
1&
03
b111 !
b111 '
1$
1"
#10
0"
#15
0/
1%
03
1$
0+
b111 !
b111 '
1&
1"
#20
0"
#25
0/
1%
0+
1&
03
b111 !
b111 '
1$
1"
#30
0"
#35
0/
1%
03
1$
0+
b111 !
b111 '
1&
1"
#40
0"
#45
0/
1%
0+
1&
03
b111 !
b111 '
1$
1"
#50
0"
#55
0/
1%
03
1$
0+
b111 !
b111 '
1&
1"
#60
0"
#65
0/
1%
0+
1&
03
b111 !
b111 '
1$
1"
#70
0"
#75
0/
1%
03
1$
0+
b111 !
b111 '
1&
1"
#80
0"
#85
0/
1%
0+
1&
03
b111 !
b111 '
1$
1"
#90
0"
#95
0/
1%
03
1$
0+
b111 !
b111 '
1&
1"
#100
0"
#105
0/
1%
0+
1&
03
b111 !
b111 '
1$
1"
#110
0"
#115
0/
1%
03
1$
0+
b111 !
b111 '
1&
1"
#120
0"
#125
0/
1%
0+
1&
03
b111 !
b111 '
1$
1"
#130
0"
#135
0/
1%
03
1$
0+
b111 !
b111 '
1&
1"
#140
0"
#145
0/
1%
0+
1&
03
b111 !
b111 '
1$
1"
#150
0"
#155
0/
1%
03
1$
0+
b111 !
b111 '
1&
1"
#160
0"
#165
0/
1%
0+
1&
03
b111 !
b111 '
1$
1"
#170
0"
#175
0/
1%
03
1$
0+
b111 !
b111 '
1&
1"
#180
0"
#185
0/
1%
0+
1&
03
b111 !
b111 '
1$
1"
#190
0"
#195
0/
1%
03
1$
0+
b111 !
b111 '
1&
1"
#200
0"
#205
0/
1%
0+
1&
03
b111 !
b111 '
1$
1"
#210
0"
#215
0/
1%
03
1$
0+
b111 !
b111 '
1&
1"
#220
0"
#225
0/
1%
0+
1&
03
b111 !
b111 '
1$
1"
#230
0"
#235
0/
1%
03
1$
0+
b111 !
b111 '
1&
1"
#240
0"
#245
0/
1%
0+
1&
03
b111 !
b111 '
1$
1"
