100_days_grind/modn_counter/pre_clr_jk.sv
module pre_clr (q,qbar,clk,pre,clr,j,k);
input clk,pre,clr,j,k;
output reg q = 0, qbar = 1;

    always @( posedge clk) begin
        case ({j,k})
        2'b00 : q = q;
        2'b01 : q = 0;
        2'b10 : q = 1;
        2'b11 : q = ~q;
        endcase
        qbar = ~q;
    end
 
    always @ (*) begin 
        if (pre == 0)
        q = 1;
        else if (clr == 0)
        q = 0;
        else
        q = q;

        qbar = ~q;
    end
endmodule

100_days_grind/modn_counter/modn_count.sv
// THis is a mod n counter or to be specific it counts to a perticular value.
// In this example the counter counts till 5 and then resets back;

module modn_counter (clk,out);

input clk;
output [2:0]out;
wire w1,w2,w3,wz;

assign wz = w1 & ~w2 & ~w3;
pre_clr gh (.j(1'b1),.k(1'b1),.pre(1'b1),.clr(wz),.clk(clk),.q(w1));
pre_clr hj (.j(1'b1),.k(1'b1),.pre(1'b1),.clr(wz),.clk(w1),.q(w2));
pre_clr op (.j(1'b1),.k(1'b1),.pre(1'b1),.clr(wz),.clk(w2),.q(w3));
assign out[0] = w1;
assign out[1] = w2;
assign out[2] = w3;
endmodule

100_days_grind/modn_counter/modn_count_tb.sv
module modn_coun_tb();
reg clk;
wire [2:0]out;

modn_counter yu(.clk(clk),.out(out));

initial begin
    clk = 0; #250
    $finish;
end

always #5 clk = ~clk;

initial begin
    $dumpfile("modn_count.vcd");
    $dumpvars;
end

endmodule

100_days_grind/modn_counter/modn_count.vcd
$date
	Wed Sep 13 21:57:40 2023
$end
$version
	Icarus Verilog
$end
$timescale
	1s
$end
$scope module modn_coun_tb $end
$var wire 3 ! out [2:0] $end
$var reg 1 " clk $end
$scope module yu $end
$var wire 1 " clk $end
$var wire 1 # wz $end
$var wire 1 $ w3 $end
$var wire 1 % w2 $end
$var wire 1 & w1 $end
$var wire 3 ' out [2:0] $end
$scope module gh $end
$var wire 1 " clk $end
$var wire 1 # clr $end
$var wire 1 ( j $end
$var wire 1 ) k $end
$var wire 1 * pre $end
$var reg 1 & q $end
$var reg 1 + qbar $end
$upscope $end
$scope module hj $end
$var wire 1 & clk $end
$var wire 1 # clr $end
$var wire 1 , j $end
$var wire 1 - k $end
$var wire 1 . pre $end
$var reg 1 % q $end
$var reg 1 / qbar $end
$upscope $end
$scope module op $end
$var wire 1 % clk $end
$var wire 1 # clr $end
$var wire 1 0 j $end
$var wire 1 1 k $end
$var wire 1 2 pre $end
$var reg 1 $ q $end
$var reg 1 3 qbar $end
$upscope $end
$upscope $end
$upscope $end
$enddefinitions $end
#0
$dumpvars
13
12
11
10
1/
1.
1-
1,
1+
1*
1)
1(
b0 '
0&
0%
0$
0#
0"
b0 !
$end
#5
13
0$
0#
1/
0%
1+
b0 !
b0 '
0&
1"
#10
0"
#15
13
0$
0#
1/
0%
1+
b0 !
b0 '
0&
1"
#20
0"
#25
13
0$
0#
1/
0%
1+
b0 !
b0 '
0&
1"
#30
0"
#35
13
0$
0#
1/
0%
1+
b0 !
b0 '
0&
1"
#40
0"
#45
13
0$
0#
1/
0%
1+
b0 !
b0 '
0&
1"
#50
0"
#55
13
0$
0#
1/
0%
1+
b0 !
b0 '
0&
1"
#60
0"
#65
13
0$
0#
1/
0%
1+
b0 !
b0 '
0&
1"
#70
0"
#75
13
0$
0#
1/
0%
1+
b0 !
b0 '
0&
1"
#80
0"
#85
13
0$
0#
1/
0%
1+
b0 !
b0 '
0&
1"
#90
0"
#95
13
0$
0#
1/
0%
1+
b0 !
b0 '
0&
1"
#100
0"
#105
13
0$
0#
1/
0%
1+
b0 !
b0 '
0&
1"
#110
0"
#115
13
0$
0#
1/
0%
1+
b0 !
b0 '
0&
1"
#120
0"
#125
13
0$
0#
1/
0%
1+
b0 !
b0 '
0&
1"
#130
0"
#135
13
0$
0#
1/
0%
1+
b0 !
b0 '
0&
1"
#140
0"
#145
13
0$
0#
1/
0%
1+
b0 !
b0 '
0&
1"
#150
0"
#155
13
0$
0#
1/
0%
1+
b0 !
b0 '
0&
1"
#160
0"
#165
13
0$
0#
1/
0%
1+
b0 !
b0 '
0&
1"
#170
0"
#175
13
0$
0#
1/
0%
1+
b0 !
b0 '
0&
1"
#180
0"
#185
13
0$
0#
1/
0%
1+
b0 !
b0 '
0&
1"
#190
0"
#195
13
0$
0#
1/
0%
1+
b0 !
b0 '
0&
1"
#200
0"
#205
13
0$
0#
1/
0%
1+
b0 !
b0 '
0&
1"
#210
0"
#215
13
0$
0#
1/
0%
1+
b0 !
b0 '
0&
1"
#220
0"
#225
13
0$
0#
1/
0%
1+
b0 !
b0 '
0&
1"
#230
0"
#235
13
0$
0#
1/
0%
1+
b0 !
b0 '
0&
1"
#240
0"
#245
13
0$
0#
1/
0%
1+
b0 !
b0 '
0&
1"
